face_recognition/__init__.py
face_recognition/face_recognizers.py
face_recognition/face_space.py
face_recognition/classifiers/__init__.py
face_recognition/classifiers/distance_classifier.py
face_recognition/classifiers/one_neighbor_classifier.py
face_recognition/helpers/__init__.py
face_recognition/helpers/simple_metric_report.py
pl_face_recognition-0.1.0.dist-info/LICENSE
pl_face_recognition-0.1.0.dist-info/METADATA
pl_face_recognition-0.1.0.dist-info/WHEEL
pl_face_recognition-0.1.0.dist-info/top_level.txt
pl_face_recognition-0.1.0.dist-info/RECORD
